{
  "$schema": "https://mintlify.com/schema.json",
  "name": "Welcome to the Junction",
  "logo": {
    "dark": "/logo/dark.svg",
    "light": "/logo/light.svg"
  },
  "favicon": "/favicon.svg",
  "colors": {
    "primary": "#FF3049",
    "light": "#FF576C",
    "dark": "#FF3049",
    "anchors": {
      "from": "#FF3049",
      "to": "#FF3049"
    }
  },
  "theme": {
  "colors": {
    "light": {
      "background": "#FFFFFF"
    },
    "dark": {
      "background": "#110808"
    }
  }
},
  "topbarLinks": [
    {
      "name": "Support",
      "url": "mailto:gm@junction.exchange"
    }
  ],
  "topbarCtaButton": {
    "name": "Try our exchange",
    "url": "https://app.junction.exchange"
  },
  "tabs": [
    {
      "name": "API Reference",
      "url": "api-reference"
    },
    {
      "name": "Integrations",
      "url": "integrations"
    }
  ],
  "anchors": [
    {
      "name": "Social",
      "icon": "X",
      "url": "https://x.com/junctionfi"
    },
    {
      "name": "Users community",
      "icon": "Telegram",
      "url": "https://t.me/junctionfi"
    },
    {
      "name": "Devs community",
      "icon": "Discord",
      "url": "https://discord.gg/nwhVduWqE8"
    },
    {
      "name": "Newsletter",
      "icon": "Newspaper",
      "url": "https://newsletter.junction.exchange"
    }
  ],
  "navigation": [
    {
      "group": "Welcome to the Junction",
      "pages": [
        "introduction",
        "what-is-junction",
        "junction-contracts",
        "jun-tokenomics"
      ]
    },
    {
      "group": "Junction API",
      "pages": [
        "junction-api/introduction"
      ]
    },
    {
      "group": "Junction Exchange",
      "pages": [
        "junction-exchange/introduction",
        "junction-exchange/platform-fee",
        "junction-exchange/how-to-connect",
        "junction-exchange/how-to-make-a-swap",
        "junction-exchange/how-to-buy-crypto",
        "junction-exchange/supported-blockchains"
      ]
    },
    {
      "group": "Junction Connector",
      "pages": [
        "junction-connector/introduction",
        "junction-connector/supported-ecosystems",
        "junction-connector/supported-wallets"
      ]
    },
    {
      "group": "Junction Earn",
      "pages": [
        "junction-earn/introduction",
        "junction-earn/what-is-xp"
      ]
    },
    {
      "group": "API Documentation",
      "pages": [
        "api-reference/introduction"
      ]
    },
    {
      "group": "Endpoint Examples",
      "pages": [
        "api-reference/endpoint/graphql"
      ]
    },
    {
      "group": "Integrations",
      "pages": [
        "integrations/introduction"
      ]
    }
  ],
  "footerSocials": {
    "website": "https://junction.exchange",
    "x": "https://x.com/junctionfi",
    "github": "https://github.com/junction-exchange",
    "discord": "https://discord.gg/nwhVduWqE8",
    "linkedin": "https://www.linkedin.com/company/junction-exchange"
  },
  "api": {
    "baseUrl": "https://router-dev.junction.exchange/graphql"
  }
}